LICENSE
MANIFEST.in
README.md
pyproject.toml
setup.cfg
setup.py
maintenance/__init__.py
maintenance/apps.py
maintenance/consumers.py
maintenance/forms.py
maintenance/keys.py
maintenance/locks.py
maintenance/menu.py
maintenance/middleware.py
maintenance/models.py
maintenance/modes.py
maintenance/settings.py
maintenance/urls.py
maintenance/views.py
maintenance/wagtail_hooks.py
maintenance/locale/nl/LC_MESSAGES/django.mo
maintenance/locale/nl/LC_MESSAGES/django.po
maintenance/migrations/0001_initial.py
maintenance/migrations/0002_alter_permissiononlymodel_options.py
maintenance/migrations/0003_alter_permissiononlymodel_options.py
maintenance/migrations/__init__.py
maintenance/migrations/__pycache__/0001_initial.cpython-311.pyc
maintenance/migrations/__pycache__/0002_alter_permissiononlymodel_options.cpython-311.pyc
maintenance/migrations/__pycache__/0003_alter_permissiononlymodel_options.cpython-311.pyc
maintenance/migrations/__pycache__/__init__.cpython-311.pyc
maintenance/static/maintenance/admin/maintenance.css
maintenance/static/maintenance/css/maintenance.css
maintenance/templates/maintenance/maintenance_mode.html
maintenance/templates/maintenance/maintenance_mode_admin.html
maintenance/templates/wagtailadmin/base.html
maintenance/templatetags/__init__.py
maintenance/templatetags/maintenance_tags.py
maintenance/templatetags/__pycache__/__init__.cpython-311.pyc
maintenance/templatetags/__pycache__/maintenance_tags.cpython-311.pyc
wagtail_maintenance.egg-info/PKG-INFO
wagtail_maintenance.egg-info/SOURCES.txt
wagtail_maintenance.egg-info/dependency_links.txt
wagtail_maintenance.egg-info/requires.txt
wagtail_maintenance.egg-info/top_level.txt